pae_toolkit/__init__.py
pae_toolkit/check_env.py
pae_toolkit/gen_dataset_by_gsm8k.py
pae_toolkit/gen_rank_table.py
pae_toolkit/qwen2audio7b.py
pae_toolkit/pd/__init__.py
pae_toolkit/pd/single-container/run.sh
pae_toolkit/pd/single-container/start-pd-server.sh
pae_toolkit/pd/single-container/conf/config_d0.json
pae_toolkit/pd/single-container/conf/config_d0.json:Zone.Identifier
pae_toolkit/pd/single-container/conf/config_p0.json
pae_toolkit/pd/single-container/conf/config_p0.json:Zone.Identifier
pae_toolkit/pd/single-container/conf/global_rank_table_file.json
pae_toolkit/pd/single-container/conf/ms_controller.json
pae_toolkit/pd/single-container/conf/ms_controller.json:Zone.Identifier
pae_toolkit/pd/single-container/conf/ms_coordinator.json
pae_toolkit/pd/single-container/conf/ms_coordinator.json:Zone.Identifier
pae_toolkit/util/timer.py
pae_toolkit-0.0.6.dist-info/METADATA
pae_toolkit-0.0.6.dist-info/WHEEL
pae_toolkit-0.0.6.dist-info/entry_points.txt
pae_toolkit-0.0.6.dist-info/RECORD
