Metadata-Version: 2.4
Name: pae-toolkit
Version: 0.0.6
Summary: PAE toolkit
Author-email: Yanguan02 <yanguan_02@126.com>
Requires-Python: >=3.9
Requires-Dist: pydantic>=2.11.5
Requires-Dist: typer>=0.16.0
